{
"*EL": "{#Delete}",
"-FRPB": "{#Tab}",
"-R": "{^}\n{^}",
"AO": "{^^}",
"AUPT": "update",
"E": "{^}{-|}",
"H*B": "{-^}",
"H*EL": "he'll",
"HOERZ": "horizontal",
"HREUPB/UBGS": "linux",
"HREUS": "list",
"HRO*ER": "{>}",
"HRO*L": "lol",
"HROEUPBGS": "GNU/Linux",
"KHRAER": "{}{^}",
"KP-BG": "excalamus",
"KP-RG": "{^}xc/{^}",
"KPA*L": "{<}",
"KPW-T": "PyQt",
"KR*D": "{^}cd",
"KR*PLD": "cd ..",
"KROERG": "kroger",
"KW-T": "Qt",
"KWA*L": "{^}={^}",
"O": "{}{-|}",
"PH*EUFBG": "misc",
"PHA*T": "matt",
"PHAEPBL": "manual",
"PHAF": "math",
"PHR*UP": "{PLOVER:LOOKUP}",
"PWHR-FRPB": "{^} {#tab} {^}",
"R-R": "{^}\n{^}",
"SKWR-FPB": "json",
"SKWRES/KA": "jessica",
"SRAOES": "visa",
"STPH*F": "{#Alt_L(BackSpace)}",
"STPHAO*EBG": "sneek",
"STPHERT": "insert",
"T-P": "{^}→{^}",
"TAOT/TPHOT": "tutanota",
"TH-FL": "{^};{^}",
"THO*PB": "python",
"TK*EL": "{#Delete}",
"TK-PB": "define",
"TKPW*/PHAEUL": "gmail",
"TKPWEBGS": "guix",
"TP*PL": "..",
"TPR*PL": "{^\\{^}",
"TPR-PL": "{^\\}^}",
"TR-Z": "trzcinski"
}
